{"is_source_file": false, "format": "", "description": "", "external_files": [], "external_methods": [], "published": [], "classes": [], "methods": [], "calls": [], "search-terms": ["tailwindcss", "CSS variables", "CSS customization", "dark mode"], "state": 2, "file_id": 12, "knowledge_revision": 25, "git_revision": "f466b55bf84c32ee22da896895431d3b29273de7", "hash": "9f5d41fce30a3372f53ad3390dafb5be", "format-version": 4, "code-base-name": "visitor_management_frontend", "filename": "visitor_management_frontend/src/app/globals.css", "revision_history": [{"25": "f466b55bf84c32ee22da896895431d3b29273de7"}]}